Workbook

Sheet INPUTS
B1: VOYAGERENT — ОСНОВНЫЕ ПАРАМЕТРЫ (INPUTS)
B2: Все данные вводятся ТОЛЬКО на этом листе. Остальные листы рассчитываются автоматически.
B3: Параметр | C3: Значение | D3: Единица | E3: Комментарий
B5: 🚗 АВТОПАРК (Fleet)
B6: Количество автомобилей | C6: 100 | D6: шт. | E6: Текущий размер автопарка
B7: Стоимость автомобиля (средняя) | C7: 18000 | D7: € | E7: Средняя закупочная цена
B8: Срок амортизации | C8: 5 | D8: лет | E8: Период списания стоимости
B9: Остаточная стоимость (%) | C9: 0.2 | D9: % | E9: % от стоимости при продаже через срок амортизации
B11: 💰 ДОХОДЫ (Revenue)
B12: Средняя цена аренды в день | C12: 45 | D12: €/день | E12: Средневзвешенная по классам авто
B13: Средняя продолжительность аренды | C13: 5 | D13: дней | E13: Средний срок одной аренды
B14: Загрузка автопарка | C14: 0.65 | D14: % | E14: % времени, когда авто сдано в аренду
B15: Количество аренд в месяц (на 1 авто) | C15: 4 | D15: шт. | E15: Среднее кол-во аренд на 1 авто в месяц
B16: Комиссия агрегаторов | C16: 0.15 | D16: % | E16: Booking, Rentalcars, Discovercars и т.д.
B18: 🔧 РАСХОДЫ НА АВТОМОБИЛЬ (Per Vehicle Costs)
B19: Страховка (на авто в месяц) | C19: 120 | D19: €/авто/мес | E19: Полная страховка + КАСКО
B20: Ремонт и обслуживание (на авто в месяц) | C20: 80 | D20: €/авто/мес | E20: Средний месячный расход
B21: Парковка (на авто в месяц) | C21: 50 | D21: €/авто/мес | E21: Стоянка / паркинг
B22: Топливо / подготовка (на авто в месяц) | C22: 40 | D22: €/авто/мес | E22: Подготовка, мойка, топливо
B23: ITV + налоги (на авто в год) | C23: 200 | D23: €/авто/год | E23: Техосмотр + транспортный налог
B25: 🏢 ОБЩИЕ РАСХОДЫ КОМПАНИИ (Overhead)
B26: Количество сотрудников | C26: 6 | D26: чел. | E26: Штат компании
B27: Средняя зарплата (gross) | C27: 1800 | D27: €/мес | E27: Зарплата до налогов
B28: Налоги на зарплату (%) | C28: 0.3 | D28: % | E28: Соц. взносы работодателя в Испании
B29: Аренда офиса / точки | C29: 1500 | D29: €/мес | E29: Офис + точки выдачи
B30: Маркетинг и реклама | C30: 2000 | D30: €/мес | E30: Google Ads, SEO, соц. сети
B31: Софт и IT | C31: 500 | D31: €/мес | E31: CRM, GPS-трекинг, бухгалтерия
B32: Связь и интернет | C32: 200 | D32: €/мес | E32: Телефония, интернет
B33: Прочие расходы | C33: 500 | D33: €/мес | E33: Непредвиденные расходы
B35: 📈 РОСТ И СЦЕНАРИИ (Growth)
B36: Планируемый рост флота (% в год) | C36: 0.2 | D36: % | E36: На сколько % вырастет флот за год
B37: Сезонность: высокий сезон (мес.) | C37: 5 | D37: мес. | E37: Кол-во месяцев высокого сезона
B38: Коэффициент высокого сезона | C38: 1.3 | D38: × | E38: Множитель загрузки в высокий сезон
B39: Коэффициент низкого сезона | C39: 0.7 | D39: × | E39: Множитель загрузки в низкий сезон
B41: 🏛️ НАЛОГИ (Tax)
B42: Ставка налога на прибыль | C42: 0.25 | D42: % | E42: Impuesto de Sociedades (Испания)
B43: НДС (IVA) | C43: 0.21 | D43: % | E43: IVA в Испании 21%

Sheet UNIT ECONOMICS
B1: UNIT ECONOMICS — Экономика одного автомобиля
B3: Показатель | C3: Значение | D3: Ед. | E3: Формула / Комментарий
B5: ДОХОД НА 1 АВТОМОБИЛЬ
B6: Доход за 1 аренду (gross) | C6: =INPUTS!C12*INPUTS!C13 | D6: € | E6: Цена/день × Дни аренды
B7: Количество аренд в месяц | C7: =INPUTS!C15 | D7: шт. | E7: Из INPUTS
B8: Месячный доход (gross) | C8: =C6*C7 | D8: € | E8: Доход за аренду × Кол-во аренд
B9: Комиссия агрегаторов | C9: =C8*INPUTS!C16 | D9: € | E9: Месячный доход × % комиссии
B10: Месячный доход (net) | C10: =C8-C9 | D10: € | E10: После вычета комиссии
B11: Годовой доход (net) | C11: =C10*12 | D11: € | E11: Месячный × 12
B13: РАСХОДЫ НА 1 АВТОМОБИЛЬ (в месяц)
B14: Амортизация (в месяц) | C14: =INPUTS!C7*(1-INPUTS!C9)/(INPUTS!C8*12) | D14: € | E14: Стоимость×(1-ост.%)/(Срок×12)
B15: Страховка | C15: =INPUTS!C19 | D15: € | E15: Из INPUTS
B16: Ремонт и обслуживание | C16: =INPUTS!C20 | D16: € | E16: Из INPUTS
B17: Парковка | C17: =INPUTS!C21 | D17: € | E17: Из INPUTS
B18: Топливо / подготовка | C18: =INPUTS!C22 | D18: € | E18: Из INPUTS
B19: ITV + налоги (в месяц) | C19: =INPUTS!C23/12 | D19: € | E19: Годовая сумма / 12
B20: ИТОГО расходы на 1 авто / мес | C20: =SUM(C14:C19) | D20: € | E20: Сумма всех расходов
B21: ИТОГО расходы на 1 авто / год | C21: =C20*12 | D21: € | E21: × 12 месяцев
B23: ПРИБЫЛЬ НА 1 АВТОМОБИЛЬ
B24: Валовая прибыль (месяц) | C24: =C10-C20 | D24: € | E24: Доход net - Расходы
B25: Валовая прибыль (год) | C25: =C24*12 | D25: € | E25: × 12
B26: Маржинальность | C26: =C24/C10 | D26: % | E26: Валовая прибыль / Доход
B28: ОКУПАЕМОСТЬ
B29: Стоимость автомобиля | C29: =INPUTS!C7 | D29: € | E29: Из INPUTS
B30: Чистая стоимость (за вычетом остат.) | C30: =INPUTS!C7*(1-INPUTS!C9) | D30: € | E30: Стоимость × (1 - ост.%)
B31: Срок окупаемости | C31: =IF(C24>0,C30/C24,"N/A") | D31: мес. | E31: Чистая стоимость / Валовая прибыль в мес.
B32: ROI (годовой) | C32: =IF(C29>0,C25/C29,0) | D32: % | E32: Годовая прибыль / Стоимость авто

Sheet FLEET PERFORMANCE
B1: FLEET PERFORMANCE — Показатели автопарка
B3: Показатель | C3: Значение | D3: Ед. | E3: Формула
B5: ОБЩИЕ ПОКАЗАТЕЛИ ФЛОТА
B6: Количество автомобилей | C6: =INPUTS!C6 | D6: шт. | E6: Из INPUTS
B7: Загрузка автопарка | C7: =INPUTS!C14 | D7: % | E7: Из INPUTS
B8: Дней аренды на 1 авто в месяц | C8: =30*INPUTS!C14 | D8: дней | E8: 30 × Загрузка
B9: Дней аренды всего флота в месяц | C9: =C8*C6 | D9: дней | E9: Дней на авто × Кол-во авто
B11: АРЕНДЫ
B12: Аренд на 1 авто в месяц | C12: =INPUTS!C15 | D12: шт. | E12: Из INPUTS
B13: Аренд на 1 авто в день | C13: =C12/30 | D13: шт. | E13: В месяц / 30
B14: Аренд всего флота в день | C14: =C13*C6 | D14: шт. | E14: На 1 авто в день × Флот
B15: Аренд всего флота в месяц | C15: =C12*C6 | D15: шт. | E15: На 1 авто в мес × Флот
B16: Аренд всего флота в год | C16: =C15*12 | D16: шт. | E16: В месяц × 12
B18: ДОХОД ФЛОТА
B19: Доход за 1 аренду (gross) | C19: =INPUTS!C12*INPUTS!C13 | D19: € | E19: Цена/день × Дни
B20: Месячный доход флота (gross) | C20: =C19*C15 | D20: € | E20: Доход за аренду × Аренды в мес
B21: Комиссия агрегаторов (мес) | C21: =C20*INPUTS!C16 | D21: € | E21: Gross × % комиссии
B22: Месячный доход флота (net) | C22: =C20-C21 | D22: € | E22: Gross - Комиссия
B23: Годовой доход флота (net) | C23: =C22*12 | D23: € | E23: × 12
B24: Средний доход на 1 авто (мес, net) | C24: =C22/C6 | D24: € | E24: Доход net / Кол-во авто
B25: Средний доход на 1 авто (год, net) | C25: =C24*12 | D25: € | E25: × 12
B27: РАСХОДЫ ФЛОТА
B28: Расходы на весь флот (мес) | C28: ='UNIT ECONOMICS'!C20*C6 | D28: € | E28: Расходы на 1 авто × Флот
B29: Расходы на весь флот (год) | C29: =C28*12 | D29: € | E29: × 12
B31: ВАЛОВАЯ ПРИБЫЛЬ ФЛОТА
B32: Валовая прибыль флота (мес) | C32: =C22-C28 | D32: € | E32: Доход net - Расходы
B33: Валовая прибыль флота (год) | C33: =C32*12 | D33: € | E33: × 12
B34: Маржинальность флота | C34: =IF(C22>0,C32/C22,0) | D34: % | E34: Валовая прибыль / Доход

Sheet REVENUE FORECAST
B1: REVENUE FORECAST — Прогноз доходов на 12 месяцев
B3: Показатель | C3: Enero | D3: Febrero | E3: Marzo | F3: Abril | G3: Mayo | H3: Junio | I3: Julio | J3: Agosto | K3: Septiembre | L3: Octubre | M3: Noviembre | N3: Diciembre | O3: ИТОГО ГОД
B4: СЕЗОННОСТЬ И ЗАГРУЗКА
B5: Сезонный коэффициент | C5: =IF(OR(1=6,1=7,1=8,1=9,1=10),INPUTS!C38,INPUTS!C39) | D5: =IF(OR(2=6,2=7,2=8,2=9,2=10),INPUTS!C38,INPUTS!C39) | E5: =IF(OR(3=6,3=7,3=8,3=9,3=10),INPUTS!C38,INPUTS!C39) | F5: =IF(OR(4=6,4=7,4=8,4=9,4=10),INPUTS!C38,INPUTS!C39) | G5: =IF(OR(5=6,5=7,5=8,5=9,5=10),INPUTS!C38,INPUTS!C39) | H5: =IF(OR(6=6,6=7,6=8,6=9,6=10),INPUTS!C38,INPUTS!C39) | I5: =IF(OR(7=6,7=7,7=8,7=9,7=10),INPUTS!C38,INPUTS!C39) | J5: =IF(OR(8=6,8=7,8=8,8=9,8=10),INPUTS!C38,INPUTS!C39) | K5: =IF(OR(9=6,9=7,9=8,9=9,9=10),INPUTS!C38,INPUTS!C39) | L5: =IF(OR(10=6,10=7,10=8,10=9,10=10),INPUTS!C38,INPUTS!C39) | M5: =IF(OR(11=6,11=7,11=8,11=9,11=10),INPUTS!C38,INPUTS!C39) | N5: =IF(OR(12=6,12=7,12=8,12=9,12=10),INPUTS!C38,INPUTS!C39)
B6: Загрузка (с учётом сезона) | C6: =INPUTS!C14*C5 | D6: =INPUTS!C14*D5 | E6: =INPUTS!C14*E5 | F6: =INPUTS!C14*F5 | G6: =INPUTS!C14*G5 | H6: =INPUTS!C14*H5 | I6: =INPUTS!C14*I5 | J6: =INPUTS!C14*J5 | K6: =INPUTS!C14*K5 | L6: =INPUTS!C14*L5 | M6: =INPUTS!C14*M5 | N6: =INPUTS!C14*N5
B7: Кол-во авто | C7: =ROUND(INPUTS!C6*(1+INPUTS!C36*0/12),0) | D7: =ROUND(INPUTS!C6*(1+INPUTS!C36*1/12),0) | E7: =ROUND(INPUTS!C6*(1+INPUTS!C36*2/12),0) | F7: =ROUND(INPUTS!C6*(1+INPUTS!C36*3/12),0) | G7: =ROUND(INPUTS!C6*(1+INPUTS!C36*4/12),0) | H7: =ROUND(INPUTS!C6*(1+INPUTS!C36*5/12),0) | I7: =ROUND(INPUTS!C6*(1+INPUTS!C36*6/12),0) | J7: =ROUND(INPUTS!C6*(1+INPUTS!C36*7/12),0) | K7: =ROUND(INPUTS!C6*(1+INPUTS!C36*8/12),0) | L7: =ROUND(INPUTS!C6*(1+INPUTS!C36*9/12),0) | M7: =ROUND(INPUTS!C6*(1+INPUTS!C36*10/12),0) | N7: =ROUND(INPUTS!C6*(1+INPUTS!C36*11/12),0)
B9: ДОХОДЫ
B10: Дней аренды (флот) | C10: =30*C6*C7 | D10: =30*D6*D7 | E10: =30*E6*E7 | F10: =30*F6*F7 | G10: =30*G6*G7 | H10: =30*H6*H7 | I10: =30*I6*I7 | J10: =30*J6*J7 | ... N10: =30*N6*N7 | O10: =SUM(C10:N10)
B11: Выручка (gross) | C11: =C10*INPUTS!C12 | D11: =D10*INPUTS!C12 | E11: =E10*INPUTS!C12 | F11: =F10*INPUTS!C12 | G11: =G10*INPUTS!C12 | H11: =H10*INPUTS!C12 | I11: =I10*INPUTS!C12 | J11: =J10*INPUTS!C12 | K11: =K10*INPUTS!C12 | L11: =L10*INPUTS!C12 | M11: =M10*INPUTS!C12 | N11: =N10*INPUTS!C12 | O11: =SUM(C11:N11)
B12: Комиссия агрегаторов | C12: =C11*INPUTS!C16 | D12: =D11*INPUTS!C16 | E12: =E11*INPUTS!C16 | F12: =F11*INPUTS!C16 | G12: =G11*INPUTS!C16 | H12: =H11*INPUTS!C16 | I12: =I11*INPUTS!C16 | J12: =J11*INPUTS!C16 | K12: =K11*INPUTS!C16 | L12: =L11*INPUTS!C16 | M12: =M11*INPUTS!C16 | N12: =N11*INPUTS!C16 | O12: =SUM(C12:N12)
B13: Выручка (net) | C13: =C11-C12 | D13: =D11-D12 | E13: =E11-E12 | F13: =F11-F12 | G13: =G11-G12 | H13: =H11-H12 | I13: =I11-I12 | J13: =J11-J12 | ... N13: =N11-N12 | O13: =SUM(C13:N13)
B15: РАСХОДЫ
B16: Расходы на авто (флот) | C16: ='UNIT ECONOMICS'!C20*C7 | D16: ='UNIT ECONOMICS'!C20*D7 | E16: ='UNIT ECONOMICS'!C20*E7 | F16: ='UNIT ECONOMICS'!C20*F7 | G16: ='UNIT ECONOMICS'!C20*G7 | H16: ='UNIT ECONOMICS'!C20*H7 | I16: ='UNIT ECONOMICS'!C20*I7 | J16: ='UNIT ECONOMICS'!C20*J7 | K16: ='UNIT ECONOMICS'!C20*K7 | L16: ='UNIT ECONOMICS'!C20*L7 | M16: ='UNIT ECONOMICS'!C20*M7 | N16: ='UNIT ECONOMICS'!C20*N7 | O16: =SUM(C16:N16)
B17: ФОТ (с налогами) | C17: =INPUTS!C26*INPUTS!C27*(1+INPUTS!C28) | D17: =INPUTS!C26*INPUTS!C27*(1+INPUTS!C28) | E17: =INPUTS!C26*INPUTS!C27*(1+INPUTS!C28) | F17: =INPUTS!C26*INPUTS!C27*(1+INPUTS!C28) | G17: =INPUTS!C26*INPUTS!C27*(1+INPUTS!C28) | H17: =INPUTS!C26*INPUTS!C27*(1+INPUTS!C28) | I17: =INPUTS!C26*INPUTS!C27*(1+INPUTS!C28) | J17: =INPUTS!C26*INPUTS!C27*(1+INPUTS!C28) | K17: =INPUTS!C26*INPUTS!C27*(1+INPUTS!C28) | L17: =INPUTS!C26*INPUTS!C27*(1+INPUTS!C28) | M17: =INPUTS!C26*INPUTS!C27*(1+INPUTS!C28) | N17: =INPUTS!C26*INPUTS!C27*(1+INPUTS!C28) | O17: =SUM(C17:N17)
B18: Аренда офиса | C18: =INPUTS!C29 | D18: =INPUTS!C29 | E18: =INPUTS!C29 | F18: =INPUTS!C29 | G18: =INPUTS!C29 | H18: =INPUTS!C29 | I18: =INPUTS!C29 | J18: =INPUTS!C29 | K18: =INPUTS!C29 | L18: =INPUTS!C29 | M18: =INPUTS!C29 | N18: =INPUTS!C29 | O18: =SUM(C18:N18)
B19: Маркетинг | C19: =INPUTS!C30 | D19: =INPUTS!C30 | E19: =INPUTS!C30 | F19: =INPUTS!C30 | G19: =INPUTS!C30 | H19: =INPUTS!C30 | I19: =INPUTS!C30 | J19: =INPUTS!C30 | K19: =INPUTS!C30 | L19: =INPUTS!C30 | M19: =INPUTS!C30 | N19: =INPUTS!C30 | O19: =SUM(C19:N19)
B20: Софт + Связь + Прочие | C20: =INPUTS!C31+INPUTS!C32+INPUTS!C33 | D20: =INPUTS!C31+INPUTS!C32+INPUTS!C33 | E20: =INPUTS!C31+INPUTS!C32+INPUTS!C33 | F20: =INPUTS!C31+INPUTS!C32+INPUTS!C33 | G20: =INPUTS!C31+INPUTS!C32+INPUTS!C33 | H20: =INPUTS!C31+INPUTS!C32+INPUTS!C33 | I20: =INPUTS!C31+INPUTS!C32+INPUTS!C33 | J20: =INPUTS!C31+INPUTS!C32+INPUTS!C33 | K20: =INPUTS!C31+INPUTS!C32+INPUTS!C33 | L20: =INPUTS!C31+INPUTS!C32+INPUTS!C33 | M20: =INPUTS!C31+INPUTS!C32+INPUTS!C33 | N20: =INPUTS!C31+INPUTS!C32+INPUTS!C33 | O20: =SUM(C20:N20)
B21: ИТОГО расходы | C21: =SUM(C16:C20) | D21: =SUM(D16:D20) | E21: =SUM(E16:E20) | F21: =SUM(F16:F20) | G21: =SUM(G16:G20) | H21: =SUM(H16:H20) | I21: =SUM(I16:I20) | J21: =SUM(J16:J20) | ... N21: =SUM(N16:N20) | O21: =SUM(C21:N21)
B23: ПРИБЫЛЬ
B24: EBITDA | C24: =C13-C21 | D24: =D13-D21 | E24: =E13-E21 | F24: =F13-F21 | G24: =G13-G21 | H24: =H13-H21 | I24: =I13-I21 | J24: =J13-J21 | ... N24: =N13-N21 | O24: =SUM(C24:N24)
B25: Маржа EBITDA | C25: =IF(C13>0,C24/C13,0) | D25: =IF(D13>0,D24/D13,0) | E25: =IF(E13>0,E24/E13,0) | F25: =IF(F13>0,F24/F13,0) | G25: =IF(G13>0,G24/G13,0) | H25: =IF(H13>0,H24/H13,0) | I25: =IF(I13>0,I24/I13,0) | J25: =IF(J13>0,J24/J13,0) | ... O25: =IF(O13>0,O24/O13,0)
B28: КВАРТАЛЬНАЯ СВОДКА
C29: Q1 | D29: Q2 | E29: Q3 | F29: Q4 | G29: ГОД
B30: Выручка net | C30: =SUM(C13:E13) | D30: =SUM(F13:H13) | E30: =SUM(I13:K13) | F30: =SUM(L13:N13) | G30: =SUM(C30:F30)
B31: Расходы | C31: =SUM(C21:E21) | D31: =SUM(F21:H21) | E31: =SUM(I21:K21) | F31: =SUM(L21:N21) | G31: =SUM(C31:F31)
B32: EBITDA | C32: =SUM(C24:E24) | D32: =SUM(F24:H24) | E32: =SUM(I24:K24) | F32: =SUM(L24:N24) | G32: =SUM(C32:F32)

Sheet P&L
B1: P&L — Отчёт о прибылях и убытках (годовой)
B3: Статья | C3: Сумма (год) | D3: % от выручки | E3: Комментарий
B5: ВЫРУЧКА
B6: Выручка (gross) | C6: ='FLEET PERFORMANCE'!C23/(1-INPUTS!C16) | D6: =IF($C$8>0,C6/$C$8,0) | E6: Годовой доход флота до комиссии
B7: Комиссия агрегаторов | C7: =C6*INPUTS!C16 | D7: =IF($C$8>0,C7/$C$8,0) | E7: % комиссии × Gross
B8: Выручка (net) | C8: =C6-C7 | D8: =IF($C$8>0,C8/$C$8,0) | E8: Gross - Комиссии
B10: СЕБЕСТОИМОСТЬ (COGS)
B11: Амортизация автопарка | C11: =INPUTS!C6*INPUTS!C7*(1-INPUTS!C9)/INPUTS!C8 | D11: =IF($C$8>0,C11/$C$8,0) | E11: Амортизация всего флота за год
B12: Страховка | C12: =INPUTS!C19*INPUTS!C6*12 | D12: =IF($C$8>0,C12/$C$8,0) | E12: На авто × Флот × 12
B13: Ремонт и обслуживание | C13: =INPUTS!C20*INPUTS!C6*12 | D13: =IF($C$8>0,C13/$C$8,0)
B14: Парковка | C14: =INPUTS!C21*INPUTS!C6*12 | D14: =IF($C$8>0,C14/$C$8,0)
B15: Топливо / подготовка | C15: =INPUTS!C22*INPUTS!C6*12 | D15: =IF($C$8>0,C15/$C$8,0)
B16: ITV + налоги | C16: =INPUTS!C23*INPUTS!C6 | D16: =IF($C$8>0,C16/$C$8,0)
B17: ИТОГО себестоимость | C17: =SUM(C11:C16) | D17: =IF($C$8>0,C17/$C$8,0)
B19: ВАЛОВАЯ ПРИБЫЛЬ | C19: =C8-C17 | D19: =IF($C$8>0,C19/$C$8,0)
B20: Маржинальность валовой прибыли | D20: =IF(C8>0,C19/C8,0) | E20: Валовая прибыль / Выручка net
B22: ОПЕРАЦИОННЫЕ РАСХОДЫ (OPEX)
B23: ФОТ (с налогами на зарплату) | C23: =INPUTS!C26*INPUTS!C27*(1+INPUTS!C28)*12 | D23: =IF($C$8>0,C23/$C$8,0) | E23: Сотрудники × ЗП × (1+налог) × 12
B24: Аренда офиса / точки | C24: =INPUTS!C29*12 | D24: =IF($C$8>0,C24/$C$8,0) | E24: × 12 месяцев
B25: Маркетинг и реклама | C25: =INPUTS!C30*12 | D25: =IF($C$8>0,C25/$C$8,0) | E25: × 12 месяцев
B26: Софт и IT | C26: =INPUTS!C31*12 | D26: =IF($C$8>0,C26/$C$8,0)
B27: Связь и интернет | C27: =INPUTS!C32*12 | D27: =IF($C$8>0,C27/$C$8,0)
B28: Прочие расходы | C28: =INPUTS!C33*12 | D28: =IF($C$8>0,C28/$C$8,0)
B29: ИТОГО OPEX | C29: =SUM(C23:C28) | D29: =IF($C$8>0,C29/$C$8,0)
B31: EBITDA | C31: =C19-C29 | D31: =IF($C$8>0,C31/$C$8,0)
B32: Маржа EBITDA | D32: =IF(C8>0,C31/C8,0)
B34: Амортизация (уже учтена в COGS) | C34: =C11 | D34: =IF($C$8>0,C34/$C$8,0) | E34: Для справки
B35: EBIT | C35: =C31 | D35: =IF($C$8>0,C35/$C$8,0) | E35: =EBITDA (аморт. уже в COGS)
B37: НАЛОГ НА ПРИБЫЛЬ | C37: =IF(C35>0,C35*INPUTS!C42,0) | D37: =IF($C$8>0,C37/$C$8,0) | E37: Ставка из INPUTS
B39: ЧИСТАЯ ПРИБЫЛЬ | C39: =C35-C37 | D39: =IF($C$8>0,C39/$C$8,0)
B40: Рентабельность чистой прибыли | D40: =IF(C8>0,C39/C8,0)

Sheet CASH FLOW
B1: CASH FLOW — Движение денежных средств (12 месяцев)
B3: Статья | C3: Enero | D3: Febrero | E3: Marzo | F3: Abril | G3: Mayo | H3: Junio | I3: Julio | J3: Agosto | K3: Septiembre | L3: Octubre | M3: Noviembre | N3: Diciembre | O3: ИТОГО
B5: ОПЕРАЦИОННЫЕ ПОСТУПЛЕНИЯ
B6: Выручка от аренды (net) | C6: ='REVENUE FORECAST'!C13 | D6: ='REVENUE FORECAST'!D13 | E6: ='REVENUE FORECAST'!E13 | F6: ='REVENUE FORECAST'!F13 | G6: ='REVENUE FORECAST'!G13 | H6: ='REVENUE FORECAST'!H13 | I6: ='REVENUE FORECAST'!I13 | J6: ='REVENUE FORECAST'!J13 | ... N6: ='REVENUE FORECAST'!N13 | O6: =SUM(C6:N6)
B7: Залоги (депозиты) — приход | C7: =300*'REVENUE FORECAST'!C7*INPUTS!C15 | D7: =300*'REVENUE FORECAST'!D7*INPUTS!C15 | E7: =300*'REVENUE FORECAST'!E7*INPUTS!C15 | F7: =300*'REVENUE FORECAST'!F7*INPUTS!C15 | G7: =300*'REVENUE FORECAST'!G7*INPUTS!C15 | H7: =300*'REVENUE FORECAST'!H7*INPUTS!C15 | I7: =300*'REVENUE FORECAST'!I7*INPUTS!C15 | J7: =300*'REVENUE FORECAST'!J7*INPUTS!C15 | K7: =300*'REVENUE FORECAST'!K7*INPUTS!C15 | L7: =300*'REVENUE FORECAST'!L7*INPUTS!C15 | M7: =300*'REVENUE FORECAST'!M7*INPUTS!C15 | N7: =300*'REVENUE FORECAST'!N7*INPUTS!C15 | O7: =SUM(C7:N7)
B8: Возврат залогов | C8: =-C7*0.95 | D8: =-D7*0.95 | E8: =-E7*0.95 | F8: =-F7*0.95 | G8: =-G7*0.95 | H8: =-H7*0.95 | I8: =-I7*0.95 | J8: =-J7*0.95 | ... N8: =-N7*0.95 | O8: =SUM(C8:N8)
B9: ИТОГО поступления | C9: =C6+C7+C8 | D9: =D6+D7+D8 | E9: =E6+E7+E8 | F9: =F6+F7+F8 | G9: =G6+G7+G8 | H9: =H6+H7+H8 | I9: =I6+I7+I8 | J9: =J6+J7+J8 | ... N9: =N6+N7+N8 | O9: =SUM(C9:N9)
B11: ОПЕРАЦИОННЫЕ РАСХОДЫ
B12: Расходы на автопарк | C12: =-'REVENUE FORECAST'!C16 | D12: =-'REVENUE FORECAST'!D16 | E12: =-'REVENUE FORECAST'!E16 | F12: =-'REVENUE FORECAST'!F16 | G12: =-'REVENUE FORECAST'!G16 | H12: =-'REVENUE FORECAST'!H16 | I12: =-'REVENUE FORECAST'!I16 | J12: =-'REVENUE FORECAST'!J16 | ... N12: =-'REVENUE FORECAST'!N16 | O12: =SUM(C12:N12)
B13: ФОТ | C13: =-'REVENUE FORECAST'!C17 | D13: =-'REVENUE FORECAST'!D17 | E13: =-'REVENUE FORECAST'!E17 | F13: =-'REVENUE FORECAST'!F17 | G13: =-'REVENUE FORECAST'!G17 | H13: =-'REVENUE FORECAST'!H17 | I13: =-'REVENUE FORECAST'!I17 | J13: =-'REVENUE FORECAST'!J17 | ... N13: =-'REVENUE FORECAST'!N17 | O13: =SUM(C13:N13)
B14: Аренда офиса | C14: =-'REVENUE FORECAST'!C18 | D14: =-'REVENUE FORECAST'!D18 | E14: =-'REVENUE FORECAST'!E18 | F14: =-'REVENUE FORECAST'!F18 | G14: =-'REVENUE FORECAST'!G18 | H14: =-'REVENUE FORECAST'!H18 | I14: =-'REVENUE FORECAST'!I18 | J14: =-'REVENUE FORECAST'!J18 | ... N14: =-'REVENUE FORECAST'!N18 | O14: =SUM(C14:N14)
B15: Маркетинг | C15: =-'REVENUE FORECAST'!C19 | D15: =-'REVENUE FORECAST'!D19 | E15: =-'REVENUE FORECAST'!E19 | F15: =-'REVENUE FORECAST'!F19 | G15: =-'REVENUE FORECAST'!G19 | H15: =-'REVENUE FORECAST'!H19 | I15: =-'REVENUE FORECAST'!I19 | J15: =-'REVENUE FORECAST'!J19 | ... N15: =-'REVENUE FORECAST'!N19 | O15: =SUM(C15:N15)
B16: Софт + Связь + Прочие | C16: =-'REVENUE FORECAST'!C20 | D16: =-'REVENUE FORECAST'!D20 | E16: =-'REVENUE FORECAST'!E20 | F16: =-'REVENUE FORECAST'!F20 | G16: =-'REVENUE FORECAST'!G20 | H16: =-'REVENUE FORECAST'!H20 | I16: =-'REVENUE FORECAST'!I20 | J16: =-'REVENUE FORECAST'!J20 | ... N16: =-'REVENUE FORECAST'!N20 | O16: =SUM(C16:N16)
B17: Налог на прибыль (квартальный) | C17: 0 | D17: 0 | E17: =-'P&L'!C37/4 | F17: 0 | G17: 0 | H17: =-'P&L'!C37/4 | I17: 0 | J17: 0 | K17: =-'P&L'!C37/4 | L17: 0 | M17: 0 | N17: =-'P&L'!C37/4 | O17: =SUM(C17:N17)
B18: ИТОГО расходы | C18: =SUM(C12:C17) | D18: =SUM(D12:D17) | E18: =SUM(E12:E17) | F18: =SUM(F12:F17) | G18: =SUM(G12:G17) | H18: =SUM(H12:H17) | I18: =SUM(I12:I17) | J18: =SUM(J12:J17) | ... N18: =SUM(N12:N17) | O18: =SUM(C18:N18)
B20: ИНВЕСТИЦИИ
B21: Покупка новых автомобилей | C21: 0 | D21: =-MAX(0,'REVENUE FORECAST'!D7-'REVENUE FORECAST'!C7)*INPUTS!C7 | E21: =-MAX(0,'REVENUE FORECAST'!E7-'REVENUE FORECAST'!D7)*INPUTS!C7 | F21: =-MAX(0,'REVENUE FORECAST'!F7-'REVENUE FORECAST'!E7)*INPUTS!C7 | G21: =-MAX(0,'REVENUE FORECAST'!G7-'REVENUE FORECAST'!F7)*INPUTS!C7 | H21: =-MAX(0,'REVENUE FORECAST'!H7-'REVENUE FORECAST'!G7)*INPUTS!C7 | I21: =-MAX(0,'REVENUE FORECAST'!I7-'REVENUE FORECAST'!H7)*INPUTS!C7 | J21: =-MAX(0,'REVENUE FORECAST'!J7-'REVENUE FORECAST'!I7)*INPUTS!C7 | K21: =-MAX(0,'REVENUE FORECAST'!K7-'REVENUE FORECAST'!J7)*INPUTS!C7 | L21: =-MAX(0,'REVENUE FORECAST'!L7-'REVENUE FORECAST'!K7)*INPUTS!C7 | M21: =-MAX(0,'REVENUE FORECAST'!M7-'REVENUE FORECAST'!L7)*INPUTS!C7 | N21: =-MAX(0,'REVENUE FORECAST'!N7-'REVENUE FORECAST'!M7)*INPUTS!C7 | O21: =SUM(C21:N21)
B22: Продажа старых авто (выручка) | C22: 0 | D22: 0 | E22: 0 | F22: 0 | G22: 0 | H22: 0 | I22: 0 | J22: 0 | K22: 0 | L22: 0 | M22: 0 | N22: 0 | O22: =SUM(C22:N22)
B24: ДЕНЕЖНЫЙ ПОТОК
B25: Операционный денежный поток | C25: =C9+C18 | D25: =D9+D18 | E25: =E9+E18 | F25: =F9+F18 | G25: =G9+G18 | H25: =H9+H18 | I25: =I9+I18 | J25: =J9+J18 | ... N25: =N9+N18 | O25: =SUM(C25:N25)
B26: Инвестиционный денежный поток | C26: =C21+C22 | D26: =D21+D22 | E26: =E21+E22 | F26: =F21+F22 | G26: =G21+G22 | H26: =H21+H22 | I26: =I21+I22 | J26: =J21+J22 | ... N26: =N21+N22 | O26: =SUM(C26:N26)
B27: ЧИСТЫЙ ДЕНЕЖНЫЙ ПОТОК | C27: =C25+C26 | D27: =D25+D26 | E27: =E25+E26 | F27: =F25+F26 | G27: =G25+G26 | H27: =H25+H26 | I27: =I25+I26 | J27: =J25+J26 | ... N27: =N25+N26 | O27: =SUM(C27:N27)
B29: Накопительный денежный поток | C29: =C27 | D29: =C29+D27 | E29: =D29+E27 | F29: =E29+F27 | G29: =F29+G27 | H29: =G29+H27 | I29: =H29+I27 | J29: =I29+J27 | K29: =J29+K27 | ... N29: =M29+N27

Sheet DASHBOARD
B1: DASHBOARD — Панель управления VoyageRent
B3: Автопарк | E3: Загрузка | H3: Цена аренды / день
C4: =INPUTS!C6 | F4: =INPUTS!C14 | I4: =INPUTS!C12
B6: Выручка (год, net) | E6: EBITDA (год) | H6: Чистая прибыль (год)
C7: ='P&L'!C8 | F7: ='P&L'!C31 | I7: ='P&L'!C39
B9: Доход на 1 авто (мес) | E9: Прибыль на 1 авто (мес) | H9: Срок окупаемости авто
C10: ='UNIT ECONOMICS'!C10 | F10: ='UNIT ECONOMICS'!C24 | I10: ='UNIT ECONOMICS'!C31
B12: ROI на автомобиль | E12: Маржа EBITDA | H12: Аренд в день (флот)
C13: ='UNIT ECONOMICS'!C32 | F13: ='P&L'!D32 | I13: ='FLEET PERFORMANCE'!C14
B50: COGS | C50: ='P&L'!C17
B51: OPEX | C51: ='P&L'!C29
B52: Налоги | C52: ='P&L'!C37

Sheet SCENARIOS
B1: SCENARIOS — Сценарный анализ
B2: Измените параметры сценариев и сравните результаты
B4: ПАРАМЕТРЫ СЦЕНАРИЕВ
B5: Параметр | C5: Pessimistic | D5: Base | E5: Optimistic
B6: Количество автомобилей | C6: 80 | D6: =INPUTS!C6 | E6: 130
B7: Цена аренды (€/день) | C7: 35 | D7: =INPUTS!C12 | E7: 55
B8: Загрузка (%) | C8: 0.5 | D8: =INPUTS!C14 | E8: 0.8
B9: Аренд в месяц (на 1 авто) | C9: 3 | D9: =INPUTS!C15 | E9: 5
B10: Комиссия агрегаторов (%) | C10: 0.2 | D10: =INPUTS!C16 | E10: 0.1
B12: РЕЗУЛЬТАТЫ СЦЕНАРИЕВ
B13: Показатель | C13: Pessimistic | D13: Base | E13: Optimistic
B14: Доход за 1 аренду | C14: =C7*INPUTS!C13 | D14: =D7*INPUTS!C13 | E14: =E7*INPUTS!C13
B15: Мес. доход на авто (gross) | C15: =C14*C9 | D15: =D14*D9 | E15: =E14*E9
B16: Мес. доход на авто (net) | C16: =C15*(1-C10) | D16: =D15*(1-D10) | E16: =E15*(1-E10)
B17: Мес. расходы на авто | C17: ='UNIT ECONOMICS'!C20 | D17: ='UNIT ECONOMICS'!C20 | E17: ='UNIT ECONOMICS'!C20
B18: Валовая прибыль на авто (мес) | C18: =C16-C17 | D18: =D16-D17 | E18: =E16-E17
B19: Выручка флота (год, net) | C19: =C16*C6*12 | D19: =D16*D6*12 | E19: =E16*E6*12
B20: Расходы на флот (год) | C20: =C17*C6*12 | D20: =D17*D6*12 | E20: =E17*E6*12
B21: OPEX (год) | C21: ='P&L'!C29 | D21: ='P&L'!C29 | E21: ='P&L'!C29
B22: EBITDA (год) | C22: =C19-C20-C21 | D22: =D19-D20-D21 | E22: =E19-E20-E21
B23: Чистая прибыль (год) | C23: =C22*(1-INPUTS!C42) | D23: =D22*(1-INPUTS!C42) | E23: =E22*(1-INPUTS!C42)
B24: Маржа EBITDA | C24: =IF(C19>0,C22/C19,0) | D24: =IF(D19>0,D22/D19,0) | E24: =IF(E19>0,E22/E19,0)
B25: Срок окупаемости авто (мес) | C25: =IF(C18>0,INPUTS!C7*(1-INPUTS!C9)/C18,"N/A") | D25: =IF(D18>0,INPUTS!C7*(1-INPUTS!C9)/D18,"N/A") | E25: =IF(E18>0,INPUTS!C7*(1-INPUTS!C9)/E18,"N/A")
B26: ROI на автомобиль (год) | C26: =IF(INPUTS!C7>0,C18*12/INPUTS!C7,0) | D26: =IF(INPUTS!C7>0,D18*12/INPUTS!C7,0) | E26: =IF(INPUTS!C7>0,E18*12/INPUTS!C7,0)
